{
    "eventIdentifier": [
        {
            "assignedIdentifier": [
                {
                    "identifier": {"value": "DIVGLAX459684657"}
                }
            ]
        },
        {
            "assignedIdentifier": [
                {
                    "identifier": {"value": "BI023884847"}
                }
            ]
        }
    ],
    "corporateAction": {
        "corporateActionType": "CashDividend",
        "exDate": "2024-12-18",
        "payDate": "2024-12-26"
    }
}
