{
    "eventIdentifier": [
        {
            "assignedIdentifier": [
                {
                    "identifier": {"value": "DIVGLAX67557645"}
                }
            ]
        },
        {
            "assignedIdentifier": [
                {
                    "identifier": {"value": "BI0232455554"}
                }
            ]
        }
    ],
    "corporateAction": {
        "corporateActionType": "CashDividend",
        "exDate": "2025-04-04",
        "payDate": "2025-04-20"
    }
}
